vic2png/__init__.py
vic2png/__main__.py
vic2png/cli.py
vic2png/convert.py
vic2png/reader.py
vic2png-0.4.1.dist-info/entry_points.txt
vic2png-0.4.1.dist-info/LICENSE
vic2png-0.4.1.dist-info/WHEEL
vic2png-0.4.1.dist-info/METADATA
vic2png-0.4.1.dist-info/RECORD
