Metadata-Version: 2.3
Name: vic2png
Version: 0.4.1
Summary: Utility for converting .VIC/.IMG images to compressed image formats.
Author-email: Jacqueline Ryan <Jacqueline.Ryan@jpl.caltech.edu>
Requires-Python: >=3.8
Classifier: Development Status :: 4 - Beta
Classifier: Intended Audience :: Science/Research
Classifier: License :: OSI Approved :: Apache Software License
Classifier: Programming Language :: Python :: 3
Classifier: Programming Language :: Python :: 3.8
Classifier: Programming Language :: Python :: 3.9
Classifier: Programming Language :: Python :: 3.10
Classifier: Programming Language :: Python :: 3.11
Classifier: Programming Language :: Python :: 3.12
Classifier: Topic :: Scientific/Engineering :: Image Processing
Requires-Dist: pvl == 1.3.2
Requires-Dist: numpy >= 1.20
Requires-Dist: pillow >= 9.0
Requires-Dist: black ; extra == "dev"
Requires-Dist: flit ; extra == "dev"
Requires-Dist: mypy ; extra == "dev"
Requires-Dist: pyright ; extra == "dev"
Requires-Dist: pytest ; extra == "dev"
Requires-Dist: pytest-cov ; extra == "dev"
Requires-Dist: ruff ; extra == "dev"
Requires-Dist: tox ; extra == "dev"
Project-URL: Homepage, https://github.com/nasa-jpl/vic2png
Project-URL: Issue Tracker, https://github.com/nasa-jpl/vic2png/issues
Project-URL: Repository, https://github.com/nasa-jpl/vic2png
Provides-Extra: dev
